swibin/CreateGraph.py
swibin/__init__.py
swibin/cli.py
swibin/color.py
swibin/describe_error.py
swibin/get_openai_key.py
swibin/version.py
swibin/wrapper.py
swibin-1.0.11.dist-info/LICENSE
swibin-1.0.11.dist-info/METADATA
swibin-1.0.11.dist-info/WHEEL
swibin-1.0.11.dist-info/entry_points.txt
swibin-1.0.11.dist-info/top_level.txt
swibin-1.0.11.dist-info/RECORD
