Metadata-Version: 2.1
Name: swibin
Version: 1.0.11
Summary: Smart error insights for Python
Author: Terminal AI
Author-email: your.email@example.com
Classifier: Programming Language :: Python :: 3
Classifier: License :: OSI Approved :: MIT License
Classifier: Operating System :: OS Independent
Requires-Python: >=3.8
License-File: LICENSE
Requires-Dist: openai ==1.3.3
Requires-Dist: python-dotenv
Requires-Dist: colorama
